{
    "arbitrationLogs": {
        "version": "1.0.0",
        "lastUpdated": "2024-11-24",
        "logs": [
            {
                "logId": "LOG-0001",
                "timestamp": "2024-11-24T10:00:00Z",
                "ruleId": "R001",
                "description": "Transaction dispute raised for transaction ID TX123456789.",
                "status": "Under Review",
                "initiator": "Node-001",
                "assignedTo": "Arbitration Node-01"
            },
            {
                "logId": "LOG-0002",
                "timestamp": "2024-11-24T11:00:00Z",
                "ruleId": "R002",
                "description": "Shard integrity conflict detected in bitShards pool.",
                "status": "Resolved",
                "initiator": "Supernode-003",
                "resolution": "Integrity checks passed. No tampering detected.",
                "resolvedBy": "Validator Node-02"
            },
            {
                "logId": "LOG-0003",
                "timestamp": "2024-11-24T12:30:00Z",
                "ruleId": "R004",
                "description": "Malicious behavior reported for Node-007.",
                "status": "Escalated",
                "initiator": "Node-005",
                "escalationLevel": "L2",
                "assignedTo": "Arbitration Council"
            }
        ]
    }
}
